{
  "captured_at": "2025-10-10T01:14:53.254642",
  "fingerprint": {
    "colorDepth": 24,
    "cookieEnabled": true,
    "deviceMemory": null,
    "doNotTrack": null,
    "hardwareConcurrency": 2,
    "language": "en-US",
    "languages": [
      "en-US",
      "en"
    ],
    "mimeTypes": [
      "application/pdf",
      "text/pdf"
    ],
    "pixelRatio": 1,
    "platform": "Linux x86_64",
    "plugins": [
      "PDF Viewer",
      "Chrome PDF Viewer",
      "Chromium PDF Viewer",
      "Microsoft Edge PDF Viewer",
      "WebKit built-in PDF"
    ],
    "screenResolution": "800x600",
    "timezone": "UTC",
    "timezoneOffset": 0,
    "userAgent": "Mozilla/5.0 (Windows NT 10.0; Win64; x64) AppleWebKit/537.36 (KHTML, like Gecko) Chrome/120.0.0.0 Safari/537.36",
    "webdriver": false
  },
  "cookies": {
    "firstmls.com": {
      "url": "https://firstmls.com",
      "actual_url": "https://firstmls.com/",
      "cookie_count": 8,
      "cookies": [
        {
          "domain": ".firstmls.com",
          "expiry": 1791594899,
          "httpOnly": false,
          "name": "zabHMBucket",
          "path": "/",
          "sameSite": "None",
          "secure": true,
          "value": "HLUjwEo"
        },
        {
          "domain": ".firstmls.com",
          "expiry": 1760072399,
          "httpOnly": false,
          "name": "zft-sdc",
          "path": "/",
          "sameSite": "None",
          "secure": true,
          "value": "isef%3Dtrue-isfr%3Dtrue-source%3Ddirect"
        },
        {
          "domain": ".firstmls.com",
          "expiry": 1760060697,
          "httpOnly": false,
          "name": "zscc6c60c4b30be4630b3fa7e3d5faf740e",
          "path": "/",
          "sameSite": "None",
          "secure": true,
          "value": "1760058897139zsc0.3029627324229267"
        },
        {
          "domain": ".firstmls.com",
          "expiry": 1791594894,
          "httpOnly": false,
          "name": "zps-tgr-dts",
          "path": "/",
          "sameSite": "None",
          "secure": true,
          "value": "sc%3D1-expAppOnNewSession%3D%5B%5D-pc%3D1-sesst%3D1760058897176"
        },
        {
          "domain": "firstmls.com",
          "expiry": 1791594894,
          "httpOnly": false,
          "name": "zabUserId",
          "path": "/",
          "sameSite": "None",
          "secure": true,
          "value": "1760058894212zabu0.034517298930048845"
        },
        {
          "domain": ".firstmls.com",
          "expiry": 1794618895,
          "httpOnly": false,
          "name": "_ga",
          "path": "/",
          "sameSite": "Lax",
          "secure": false,
          "value": "GA1.1.23685356.1760058895"
        },
        {
          "domain": ".firstmls.com",
          "expiry": 1794618895,
          "httpOnly": false,
          "name": "_ga_K8E74FCC22",
          "path": "/",
          "sameSite": "Lax",
          "secure": false,
          "value": "GS2.1.s1760058895$o1$g0$t1760058895$j60$l0$h0"
        },
        {
          "domain": ".firstmls.com",
          "expiry": 1760060693,
          "httpOnly": true,
          "name": "__cf_bm",
          "path": "/",
          "sameSite": "None",
          "secure": true,
          "value": "ogALRynLy3ET7EN_DmwQZvOnSrMDaix21WOkstA4sDA-1760058893-1.0.1.1-vrwII09ikDUQ173qjZ2Q9pW2Iy0LRaX6BoyBkxPiheTXIpvQYa5WkTfa89IAo6VyNHik7oFXI0GwjC0hkLkaa0hMw_.aZz_JTodOiw5R99Y"
        }
      ]
    },
    "firstmls.sso.remine.com": {
      "error": "HTTPConnectionPool(host='localhost', port=48259): Read timed out. (read timeout=120)"
    }
  },
  "storage": {
    "firstmls.com": {
      "url": "https://firstmls.com",
      "error": "HTTPConnectionPool(host='localhost', port=48259): Read timed out. (read timeout=120)",
      "localStorage": {},
      "sessionStorage": {}
    },
    "firstmls.sso.remine.com": {
      "url": "https://firstmls.sso.remine.com/dashboard-v2",
      "error": "HTTPConnectionPool(host='localhost', port=48259): Read timed out. (read timeout=120)",
      "localStorage": {},
      "sessionStorage": {}
    },
    "sso.remine.com": {
      "url": "https://sso.remine.com",
      "error": "HTTPConnectionPool(host='localhost', port=48259): Read timed out. (read timeout=120)",
      "localStorage": {},
      "sessionStorage": {}
    },
    "fmls.remine.com": {
      "url": "https://fmls.remine.com/daily",
      "error": "HTTPConnectionPool(host='localhost', port=48259): Read timed out. (read timeout=120)",
      "localStorage": {},
      "sessionStorage": {}
    },
    "remine.com": {
      "url": "https://remine.com",
      "error": "HTTPConnectionPool(host='localhost', port=48259): Read timed out. (read timeout=120)",
      "localStorage": {},
      "sessionStorage": {}
    }
  },
  "domains_checked": [
    "https://firstmls.com",
    "https://firstmls.sso.remine.com",
    "https://firstmls.sso.remine.com/dashboard-v2",
    "https://sso.remine.com",
    "https://fmls.remine.com",
    "https://fmls.remine.com/daily",
    "https://remine.com"
  ]
}